aiographfixed
