Metadata-Version: 2.1
Name: aiographfixed
Version: 0.2.9
Summary: asynchronous Python Telegra.ph API wrapper
Home-page: https://github.com/Lunatik-cyber/aiographfixed
Author: Alex Root Junior
Author-email: aiogram@illemius.xyz
Maintainer: Alex Root Junior <jroot.junior@gmail.com>, Yyonging <sysuduanyongqiang@163.com>
Maintainer-email: sysuduanyongqiang@163.com
License: MIT
Classifier: Development Status :: 5 - Production/Stable
Classifier: Environment :: Console
Classifier: Framework :: AsyncIO
Classifier: Intended Audience :: Developers
Classifier: Intended Audience :: System Administrators
Classifier: License :: OSI Approved :: MIT License
Classifier: Programming Language :: Python :: 3.7
Classifier: Topic :: Software Development :: Libraries :: Application Frameworks
Provides-Extra: dev
License-File: LICENSE
